generate_ledger/__init__.py
generate_ledger/cli.py
generate_ledger/compose.py
generate_ledger/compose.yml.j2
generate_ledger/docker-compose.b.yml
generate_ledger/docker-compose.yml
generate_ledger/docker-compose.yml.mako
generate_ledger/docker-compose.yml.tpl
generate_ledger/gen.py
generate_ledger/gen_config.py
generate_ledger/generate.py
generate_ledger/ledger.json
generate_ledger/ledger.py
generate_ledger/mako.template
generate_ledger/mako_render.py
generate_ledger/namespace.py
generate_ledger/render_compose.py
generate_ledger/render_template.py
generate_ledger/rippled.cfg
generate_ledger/rippled_config.py
generate_ledger/test_inliine.py
generate_ledger/testnet.py
generate_ledger/utils.py
generate_ledger/uv_publish.md
legleux_generate_ledger-0.1.2.dist-info/METADATA
legleux_generate_ledger-0.1.2.dist-info/WHEEL
legleux_generate_ledger-0.1.2.dist-info/entry_points.txt
legleux_generate_ledger-0.1.2.dist-info/RECORD
