Metadata-Version: 2.4
Name: legleux-generate-ledger
Version: 0.1.2
Summary: Add your description here
Author-email: Michael Legleux <legleux@gmail.com>
Requires-Python: >=3.11
Requires-Dist: base58>=2.1.1
Requires-Dist: click>=8.2.1
Requires-Dist: httpx>=0.28.1
Requires-Dist: platformdirs>=4.3.8
Requires-Dist: ruamel-yaml>=0.18.14
Requires-Dist: xrpl-py>=4.2.0
